pypi_project_no_license/__init__.py
pypi_project_no_license-0.1.1.dist-info/METADATA
pypi_project_no_license-0.1.1.dist-info/WHEEL
pypi_project_no_license-0.1.1.dist-info/top_level.txt
pypi_project_no_license-0.1.1.dist-info/RECORD
