Metadata-Version: 2.1
Name: pypi-project-no-license
Version: 0.1.1
Summary: PyPI minimal project with no license
Home-page: https://github.com/pilosus/pypi-project-no-license
Author: pilosus
Author-email: vrs@pilosus.org
